smtm/__init__.py
smtm/__main__.py
smtm/analyzer.py
smtm/config.py
smtm/date_converter.py
smtm/log_manager.py
smtm/operator.py
smtm/simulation_operator.py
smtm/worker.py
smtm/controller/__init__.py
smtm/controller/controller.py
smtm/controller/jpt_controller.py
smtm/controller/mass_simulator.py
smtm/controller/simulator.py
smtm/controller/telegram_controller.py
smtm/data/__init__.py
smtm/data/binance_data_provider.py
smtm/data/bithumb_data_provider.py
smtm/data/data_provider.py
smtm/data/data_provider_factory.py
smtm/data/data_repository.py
smtm/data/database.py
smtm/data/simulation_data_provider.py
smtm/data/simulation_dual_data_provider.py
smtm/data/upbit_binance_data_provider.py
smtm/data/upbit_data_provider.py
smtm/strategy/__init__.py
smtm/strategy/strategy.py
smtm/strategy/strategy_bnh.py
smtm/strategy/strategy_factory.py
smtm/strategy/strategy_hey.py
smtm/strategy/strategy_rsi.py
smtm/strategy/strategy_sas.py
smtm/strategy/strategy_sma_0.py
smtm/strategy/strategy_sma_dual_ml.py
smtm/strategy/strategy_sma_ml.py
smtm/trader/__init__.py
smtm/trader/bithumb_trader.py
smtm/trader/demo_trader.py
smtm/trader/simulation_trader.py
smtm/trader/trader.py
smtm/trader/upbit_trader.py
smtm/trader/virtual_market.py
smtm-1.6.3.dist-info/LICENSE
smtm-1.6.3.dist-info/METADATA
smtm-1.6.3.dist-info/WHEEL
smtm-1.6.3.dist-info/top_level.txt
smtm-1.6.3.dist-info/RECORD
