Metadata-Version: 2.1
Name: smtm
Version: 1.6.3
Summary: A algorithm crypto trading system.
Home-page: https://github.com/msaltnet/smtm
Author: Jeong Seongmoon
Author-email: salt.jeong@gmail.com
License: MIT License
Project-URL: Documentation, https://smtm.msalt.net/
Project-URL: Source Code, https://github.com/msaltnet/smtm
Project-URL: Issue Tracker, https://github.com/msaltnet/smtm/issues/
Keywords: crypto,algorithm,trading
Platform: UNKNOWN
Classifier: Development Status :: 5 - Production/Stable
Classifier: License :: OSI Approved :: MIT License
Classifier: Operating System :: OS Independent
Classifier: Programming Language :: Python
Requires-Dist: requests
Requires-Dist: pandas
Requires-Dist: numpy
Requires-Dist: mplfinance
Requires-Dist: matplotlib
Requires-Dist: pyjwt
Requires-Dist: python-dotenv
Requires-Dist: jupyter
Requires-Dist: psutil
Requires-Dist: coverage
Requires-Dist: scikit-learn
